exqalibur.cpython-313-darwin.so
exqalibur-1.1.0.dist-info/RECORD
exqalibur-1.1.0.dist-info/WHEEL
exqalibur-1.1.0.dist-info/top_level.txt
exqalibur-1.1.0.dist-info/METADATA
exqalibur-1.1.0.dist-info/licenses/wheel/LICENSE.md
