Metadata-Version: 2.4
Name: exqalibur
Version: 1.1.0
Summary: Cutting-edge optimization for Perceval
Author: Quandela
Author-email: Perceval.OSS@Quandela.com
License: CC BY-NC-ND 4.0
Project-URL: Homepage, https://perceval.quandela.net
Requires-Python: >=3.10
License-File: wheel/LICENSE.md
Dynamic: description
Dynamic: license
Dynamic: license-file
